mcnpy/__init__.py
mcnpy/_config.py
mcnpy/_constants.py
mcnpy/energyGrids/__init__.py
mcnpy/energyGrids/_grids.py
mcnpy/input/__init__.py
mcnpy/input/input.py
mcnpy/input/material.py
mcnpy/input/parse_input.py
mcnpy/input/parse_materials.py
mcnpy/input/pert_generator.py
mcnpy/input/perturbations.py
mcnpy/mctal/__init__.py
mcnpy/mctal/mctal.py
mcnpy/mctal/parse_mctal.py
mcnpy/sensitivities/__init__.py
mcnpy/sensitivities/sdf.py
mcnpy/sensitivities/sensitivity.py
mcnpy/sensitivities/sensitivity_processing.py
mcnpy/utils/__init__.py
mcnpy/utils/energy_grids.py
mcnpy-0.2.5.dist-info/LICENSE
mcnpy-0.2.5.dist-info/METADATA
mcnpy-0.2.5.dist-info/WHEEL
mcnpy-0.2.5.dist-info/RECORD
