Metadata-Version: 2.3
Name: mcnpy
Version: 0.2.5
Summary: 
License: GNU General Public License v3.0
Author: Juan Antonio Monleon de la Lluvia
Author-email: juanmonleon96@gmail.com
Requires-Python: >=3.12,<4.0
Classifier: License :: Other/Proprietary License
Classifier: Programming Language :: Python :: 3
Classifier: Programming Language :: Python :: 3.12
Classifier: Programming Language :: Python :: 3.13
Requires-Dist: matplotlib (>=3.10.0,<4.0.0)
Requires-Dist: pandas (>=2.2.3,<3.0.0)
Requires-Dist: xarray (>=2025.3.0,<2026.0.0)
Project-URL: Homepage, https://github.com/monleon96/MCNPy.git
